sweetpotato/__init__.py
sweetpotato/app.py
sweetpotato/components.py
sweetpotato/hooks.py
sweetpotato/management.py
sweetpotato/mixins.py
sweetpotato/navigation.py
sweetpotato/ui_kitten.py
sweetpotato/config/__init__.py
sweetpotato/config/default_settings.py
sweetpotato/config/version.py
sweetpotato/core/__init__.py
sweetpotato/core/base_components.py
sweetpotato/core/base_management.py
sweetpotato/core/build.py
sweetpotato/core/context_wrappers.py
sweetpotato/core/interfaces.py
sweetpotato/core/js_objects.py
sweetpotato/core/js_utils.py
sweetpotato/frontend/.gitignore
sweetpotato/frontend/.prettierignore
sweetpotato/frontend/.prettierrc.json
sweetpotato/frontend/App.js
sweetpotato/frontend/app.json
sweetpotato/frontend/babel.config.js
sweetpotato/frontend/package.json
sweetpotato/frontend/yarn.lock
sweetpotato/frontend/.expo/README.md
sweetpotato/frontend/.expo/packager-info.json
sweetpotato/frontend/.expo/settings.json
sweetpotato/frontend/.expo-shared/assets.json
sweetpotato/frontend/assets/adaptive-icon.png
sweetpotato/frontend/assets/favicon.png
sweetpotato/frontend/assets/icon.png
sweetpotato/frontend/assets/splash.png
sweetpotato/frontend/node_modules/react-native/ReactAndroid/src/main/third-party/android/support/v7/appcompat/aar-unpacker.py
sweetpotato/frontend/src/.gitkeep
sweetpotato/frontend/tests/App.test.js
sweetpotato/functions/__init__.py
sweetpotato/functions/authentication_functions.py
sweetpotato/functions/navigation_functions.py
sweetpotato/plugins/__init__.py
sweetpotato/plugins/authentication.py
sweetpotato/props/__init__.py
sweetpotato/props/authentication_props.py
sweetpotato/props/components_props.py
sweetpotato/props/navigation_props.py
sweetpotato/props/ui_kitten_props.py
tests/__init__.py
tests/test_backend/__init__.py
tests/test_backend/test_app.py
tests/test_backend/test_mixins.py
tests/test_backend/test_utils.py
tests/test_frontend/__init__.py
sweetpotato-0.7.0a0.dist-info/LICENSE
sweetpotato-0.7.0a0.dist-info/METADATA
sweetpotato-0.7.0a0.dist-info/WHEEL
sweetpotato-0.7.0a0.dist-info/top_level.txt
sweetpotato-0.7.0a0.dist-info/RECORD
