Metadata-Version: 2.1
Name: sweetpotato
Version: 0.7.0a0
Summary: Sweetpotato provides an intuitive wrapper around React Native.
Home-page: https://github.com/greysonlalonde/sweetpotato
Download-URL: https://github.com/greysonlalonde/sweetpotato/v0.7.0-alpha.tar.gz
Author: Greyson R. LaLonde
Author-email: "Greyson R. LaLonde" <greyson.r.lalonde@gmail.com>, Devin LaCrosse <devinlax@hotmail.com>, Corey Mutnik <cmutnik@gmail.com>
Project-URL: homepage, https://github.com/greysonlalonde/sweetpotato
Project-URL: documentation, https://sweetpotato.readthedocs.io
Project-URL: tracker, https://github.com/greysonlalonde/sweetpotato/issues
Classifier: License :: OSI Approved :: MIT License
Classifier: Development Status :: 2 - Pre-Alpha
Classifier: Programming Language :: Python
Classifier: Programming Language :: Python :: 3
Classifier: Topic :: Software Development :: Libraries :: Python Modules
Classifier: Intended Audience :: Developers
Classifier: Operating System :: Microsoft :: Windows
Classifier: Operating System :: POSIX :: Linux
Classifier: Operating System :: POSIX
Classifier: Operating System :: Unix
Classifier: Operating System :: MacOS
Requires-Python: >=3.8
License-File: LICENSE
Requires-Dist: pydantic[dotenv,email] (>=1.10.2)
Provides-Extra: dev
Requires-Dist: mypy (==0.971) ; extra == 'dev'
Requires-Dist: black (==22.6.0) ; extra == 'dev'
Requires-Dist: pylint (==2.14.5) ; extra == 'dev'
Requires-Dist: isort (==5.10.1) ; extra == 'dev'
Requires-Dist: flake8 (==5.0.4) ; extra == 'dev'
Requires-Dist: autoflake (==1.5.3) ; extra == 'dev'
Provides-Extra: doc
Requires-Dist: Sphinx (==4.5.0) ; extra == 'doc'
Requires-Dist: furo (==2022.6.21) ; extra == 'doc'
Requires-Dist: sphinx-copybutton (==0.5.0) ; extra == 'doc'
Requires-Dist: sphinxext-opengraph (==0.6.3) ; extra == 'doc'
Requires-Dist: sphinx-design (==0.2.0) ; extra == 'doc'
